{
  "problem_id": "P3_1_01_00040_00470",
  "view_box": {
    "width": 900.0,
    "height": 230.0,
    "background": "#FFFFFF"
  },
  "elements": [
    {
      "id": "slot.question.text",
      "type": "text_box",
      "attributes": {
        "x": 48.0,
        "y": 30.0,
        "fill": "#202124",
        "font-family": "Noto Sans KR",
        "font-size": 24,
        "width": 804.0,
        "height": 80.0,
        "max_width": 804.0,
        "data-slot-kind": "text_box",
        "data-box-x": 48.0,
        "data-box-y": 30.0,
        "data-box-width": 804.0,
        "data-box-height": 80.0,
        "data-text-align": "left",
        "data-vertical-align": "top",
        "data-line-height": 1.5
      },
      "source_ref": "slot.question",
      "refs": {
        "layout_slot_id": "slot.question"
      },
      "text": "진이네 과수원에서는 작년에 사과 725개를 수확하였고, 올해는 작년보다 287개를 더 수확하였습니다. 올해에 수확한 사과는 모두 몇 개입니까?"
    }
  ],
  "contract_version": "modu_math.renderer.v2"
}
