{
  "problem_id": "P3_1_01_00040_02162",
  "view_box": {
    "width": 360.0,
    "height": 145.0,
    "background": "#FFFFFF"
  },
  "elements": [
    {
      "id": "slot.instruction.text",
      "type": "text_box",
      "attributes": {
        "x": 20.0,
        "y": 8.0,
        "fill": "#111111",
        "font-family": "Noto Sans KR, sans-serif",
        "font-size": 18,
        "width": 220.0,
        "height": 30.0,
        "max_width": 220.0,
        "data-slot-kind": "text_box",
        "data-box-x": 20.0,
        "data-box-y": 8.0,
        "data-box-width": 220.0,
        "data-box-height": 30.0,
        "data-text-align": "left",
        "data-vertical-align": "top",
        "data-line-height": 1.2,
        "data-semantic-role": "instruction"
      },
      "source_ref": "slot.instruction",
      "refs": {
        "layout_slot_id": "slot.instruction"
      },
      "text": "다음 덧셈을 하시오."
    },
    {
      "id": "slot.line_1.line",
      "type": "line",
      "attributes": {
        "x1": 41.431,
        "y1": 106.911,
        "x2": 103.431,
        "y2": 106.911,
        "stroke": "#111111",
        "stroke-width": 1.5
      },
      "source_ref": "slot.line_1",
      "refs": {
        "layout_slot_id": "slot.line_1"
      }
    },
    {
      "id": "slot.line_2.line",
      "type": "line",
      "attributes": {
        "x1": 164.431,
        "y1": 106.911,
        "x2": 226.431,
        "y2": 106.911,
        "stroke": "#111111",
        "stroke-width": 1.5
      },
      "source_ref": "slot.line_2",
      "refs": {
        "layout_slot_id": "slot.line_2"
      }
    },
    {
      "id": "slot.label_1.text",
      "type": "text",
      "attributes": {
        "x": 22.431,
        "y": 62.911,
        "fill": "#111111",
        "font-family": "Noto Sans KR, sans-serif",
        "font-size": 18,
        "text-anchor": "start"
      },
      "source_ref": "slot.label_1",
      "refs": {
        "layout_slot_id": "slot.label_1"
      },
      "text": "(1)"
    },
    {
      "id": "slot.addend_1_1.text",
      "type": "text",
      "attributes": {
        "x": 100.431,
        "y": 62.911,
        "fill": "#111111",
        "font-family": "Noto Sans KR, sans-serif",
        "font-size": 21,
        "text-anchor": "end"
      },
      "source_ref": "slot.addend_1_1",
      "refs": {
        "layout_slot_id": "slot.addend_1_1"
      },
      "text": "235"
    },
    {
      "id": "slot.plus_1.text",
      "type": "text",
      "attributes": {
        "x": 52.431,
        "y": 92.911,
        "fill": "#111111",
        "font-family": "Noto Sans KR, sans-serif",
        "font-size": 21,
        "text-anchor": "middle"
      },
      "source_ref": "slot.plus_1",
      "refs": {
        "layout_slot_id": "slot.plus_1"
      },
      "text": "+"
    },
    {
      "id": "slot.addend_1_2.text",
      "type": "text",
      "attributes": {
        "x": 100.431,
        "y": 92.911,
        "fill": "#111111",
        "font-family": "Noto Sans KR, sans-serif",
        "font-size": 21,
        "text-anchor": "end"
      },
      "source_ref": "slot.addend_1_2",
      "refs": {
        "layout_slot_id": "slot.addend_1_2"
      },
      "text": "486"
    },
    {
      "id": "slot.label_2.text",
      "type": "text",
      "attributes": {
        "x": 145.431,
        "y": 62.911,
        "fill": "#111111",
        "font-family": "Noto Sans KR, sans-serif",
        "font-size": 18,
        "text-anchor": "start"
      },
      "source_ref": "slot.label_2",
      "refs": {
        "layout_slot_id": "slot.label_2"
      },
      "text": "(2)"
    },
    {
      "id": "slot.addend_2_1.text",
      "type": "text",
      "attributes": {
        "x": 223.431,
        "y": 62.911,
        "fill": "#111111",
        "font-family": "Noto Sans KR, sans-serif",
        "font-size": 21,
        "text-anchor": "end"
      },
      "source_ref": "slot.addend_2_1",
      "refs": {
        "layout_slot_id": "slot.addend_2_1"
      },
      "text": "529"
    },
    {
      "id": "slot.plus_2.text",
      "type": "text",
      "attributes": {
        "x": 175.431,
        "y": 92.911,
        "fill": "#111111",
        "font-family": "Noto Sans KR, sans-serif",
        "font-size": 21,
        "text-anchor": "middle"
      },
      "source_ref": "slot.plus_2",
      "refs": {
        "layout_slot_id": "slot.plus_2"
      },
      "text": "+"
    },
    {
      "id": "slot.addend_2_2.text",
      "type": "text",
      "attributes": {
        "x": 223.431,
        "y": 92.911,
        "fill": "#111111",
        "font-family": "Noto Sans KR, sans-serif",
        "font-size": 21,
        "text-anchor": "end"
      },
      "source_ref": "slot.addend_2_2",
      "refs": {
        "layout_slot_id": "slot.addend_2_2"
      },
      "text": "898"
    }
  ],
  "contract_version": "modu_math.renderer.v2"
}
