{
  "problem_id": "P3_1_01_00040_15596",
  "view_box": {
    "width": 960.0,
    "height": 210.0,
    "background": "#FFFFFF"
  },
  "elements": [
    {
      "id": "slot.question.text",
      "type": "text",
      "attributes": {
        "x": 30.0,
        "y": 35.0,
        "fill": "#111111",
        "font-family": "Noto Sans KR, sans-serif",
        "font-size": 24
      },
      "source_ref": "slot.question",
      "refs": {
        "layout_slot_id": "slot.question"
      },
      "text": "백의 자리 숫자가 4, 십의 자리 숫자가 3, 일의 자리 숫자가 5인 수보다 534 많은 수는 얼마입니까?"
    }
  ],
  "contract_version": "modu_math.renderer.v2"
}
