{
  "schema": "modu.solvable.v1.1",
  "problem_id": "S3_초등_3_008706",
  "problem_type": "도형_컴퍼스_중심찾기",
  "inputs": {
    "total_ticks": 0,
    "target_label": "컴퍼스의 침을 꽂지 않은 곳",
    "target_ticks": 1,
    "target_count": 4,
    "unit": ""
  },
  "given": [
    {
      "ref": "obj.shape",
      "value": {
        "name": "야구공 모양"
      }
    },
    {
      "ref": "obj.choice.k",
      "value": {
        "label": "ㄱ"
      }
    },
    {
      "ref": "obj.choice.n",
      "value": {
        "label": "ㄴ"
      }
    },
    {
      "ref": "obj.choice.d",
      "value": {
        "label": "ㄷ"
      }
    },
    {
      "ref": "obj.choice.r",
      "value": {
        "label": "ㄹ"
      }
    }
  ],
  "target": {
    "ref": "answer.target",
    "type": "selected_symbol"
  },
  "method": "figure_based_selection",
  "plan": [
    "그림에서 보이는 후보 기호를 확인한다.",
    "인쇄된 해설과 정답 표기를 기준으로 선택 결과를 정리한다."
  ],
  "steps": [
    {
      "id": "step.1",
      "expr": "인쇄된 정답 표기 확인",
      "value": "ㄷ"
    },
    {
      "id": "step.2",
      "expr": "인쇄된 해설 확인",
      "value": "점 ㄷ을 원의 중심으로 하여 그린 원은 없습니다."
    }
  ],
  "checks": [
    {
      "id": "check.1",
      "expr": "정답 표기가 ㄷ인지 확인",
      "expected": "ㄷ",
      "actual": "ㄷ",
      "pass": true
    }
  ],
  "answer": {
    "blanks": [],
    "choices": [],
    "answer_key": [],
    "target": {
      "type": "selected_symbol",
      "description": "컴퍼스의 침을 꽂지 않은 곳의 기호"
    },
    "value": 3,
    "unit": ""
  }
}
