{
  "problem_id": "S3_초등_3_008572",
  "problem_type": "multiple_choice",
  "metadata": {
    "title": "계산에서 □ 안의 두 수의 곱은 실제로 얼마를 나타낼까요?",
    "tags": [],
    "question": "계산에서 □ 안의 두 수의 곱은 실제로 얼마를 나타낼까요?",
    "required_layout_ids": [
      "box_frame",
      "boxed_3",
      "boxed_4",
      "mul_bar"
    ],
    "extraction_confidence": 1.0,
    "grade": 3,
    "subject": "수학"
  },
  "domain": {
    "objects": [
      "자리값을 나타내는 숫자",
      "곱셈 도식",
      "객관식 선택지"
    ],
    "relations": [],
    "confidence": 1.0,
    "problem_solving": {
      "understand": "도식 속 숫자가 무엇을 나타내는지 자리값 관점에서 해석한다.",
      "plan": "보이는 해설 문장을 참고해 곱의 실제 의미를 이해한다.",
      "execute": "선택지 중 해설과 일치하는 값을 찾는다.",
      "review": "정답 표시와 해설 문장이 서로 맞는지 확인한다."
    }
  },
  "answer": {
    "blanks": [],
    "choices": [],
    "answer_key": [],
    "confidence": 1.0,
    "target": {
      "type": "selected_option",
      "description": "도식이 실제로 나타내는 곱의 값"
    },
    "value": 120,
    "unit": ""
  }
}
