{
  "schema": "modu.solvable.v1.1",
  "problem_id": "S3_초등_3_008586",
  "problem_type": "multiple_choice_division",
  "inputs": {
    "total_ticks": 0,
    "target_label": "ㄴ",
    "target_ticks": 0,
    "target_count": 1,
    "unit": ""
  },
  "given": [
    {
      "ref": "obj.choice_a",
      "value": {
        "label": "ㄱ",
        "dividend": 16,
        "divisor": 3
      }
    },
    {
      "ref": "obj.choice_b",
      "value": {
        "label": "ㄴ",
        "dividend": 49,
        "divisor": 7
      }
    }
  ],
  "target": {
    "ref": "answer.target",
    "type": "selected_choice"
  },
  "method": "check_remainder",
  "plan": [
    "각 나눗셈의 나머지를 확인한다.",
    "나머지가 0인 선택지를 고른다."
  ],
  "steps": [
    {
      "id": "step.1",
      "expr": "16 ÷ 3",
      "value": {
        "quotient": 5,
        "remainder": 1
      }
    },
    {
      "id": "step.2",
      "expr": "49 ÷ 7",
      "value": {
        "quotient": 7,
        "remainder": 0
      }
    },
    {
      "id": "step.3",
      "expr": "나머지가 0인 선택지",
      "value": "ㄴ"
    }
  ],
  "checks": [
    {
      "id": "check.1",
      "expr": "16 ÷ 3의 나머지",
      "expected": 1,
      "actual": 1,
      "pass": true
    },
    {
      "id": "check.2",
      "expr": "49 ÷ 7의 나머지",
      "expected": 0,
      "actual": 0,
      "pass": true
    }
  ],
  "answer": {
    "blanks": [],
    "choices": [],
    "answer_key": [],
    "target": {
      "type": "selected_choice",
      "description": "나누어떨어지는 나눗셈"
    },
    "value": "ㄴ",
    "unit": ""
  }
}
