{
  "problem_id": "S3_초등_3_008573",
  "problem_type": "순서 고르기",
  "metadata": {
    "title": "계산 결과가 큰 것부터 순서 고르기",
    "tags": [],
    "question": "계산 결과가 큰 것부터 차례대로 나타낸 것을 고르세요.",
    "required_layout_ids": [
      "slot.main_box"
    ],
    "extraction_confidence": 1.0,
    "grade": 3,
    "subject": "수학",
    "visible_answer": "③"
  },
  "domain": {
    "objects": [
      {
        "id": "expr_g",
        "type": "multiplication",
        "text": "42 × 83"
      },
      {
        "id": "expr_n",
        "type": "multiplication",
        "text": "58 × 55"
      },
      {
        "id": "expr_d",
        "type": "multiplication",
        "text": "67 × 54"
      },
      {
        "id": "expr_r",
        "type": "multiplication",
        "text": "91 × 37"
      }
    ],
    "relations": [],
    "confidence": 1.0,
    "problem_solving": {
      "understand": "각 곱셈식의 계산 결과를 비교하여 큰 순서대로 배열하는 문제이다.",
      "plan": "네 식의 결과값을 비교하여 내림차순 순서를 구한다.",
      "execute": "가장 큰 값부터 기호 순서를 정해 보기와 대조한다.",
      "review": "선택한 보기와 계산 결과의 내림차순이 일치하는지 확인한다."
    }
  },
  "answer": {
    "blanks": [],
    "choices": [],
    "answer_key": [],
    "confidence": 1.0,
    "target": {
      "type": "selected_option",
      "description": "큰 값부터의 기호 순서"
    },
    "value": "③",
    "unit": ""
  }
}
